odoo/addons/shopinvader_import_image/README.rst
odoo/addons/shopinvader_import_image/__init__.py
odoo/addons/shopinvader_import_image/__manifest__.py
odoo/addons/shopinvader_import_image/data/ir_cron.xml
odoo/addons/shopinvader_import_image/data/queue_job_channel_data.xml
odoo/addons/shopinvader_import_image/data/queue_job_function_data.xml
odoo/addons/shopinvader_import_image/i18n/shopinvader_import_image.pot
odoo/addons/shopinvader_import_image/models/__init__.py
odoo/addons/shopinvader_import_image/models/import_image.py
odoo/addons/shopinvader_import_image/readme/CONTRIBUTORS.rst
odoo/addons/shopinvader_import_image/readme/DESCRIPTION.rst
odoo/addons/shopinvader_import_image/security/ir_model_access.xml
odoo/addons/shopinvader_import_image/static/description/index.html
odoo/addons/shopinvader_import_image/tests/__init__.py
odoo/addons/shopinvader_import_image/tests/test_import_image.py
odoo/addons/shopinvader_import_image/tests/fixture/A001.jpg
odoo/addons/shopinvader_import_image/tests/fixture/A002.jpg
odoo/addons/shopinvader_import_image/tests/fixture/A003.jpg
odoo/addons/shopinvader_import_image/tests/fixture/image_import_test.csv
odoo/addons/shopinvader_import_image/tests/fixture/image_import_test.zip
odoo/addons/shopinvader_import_image/views/import_product_image_view.xml
odoo/addons/shopinvader_import_image/views/report_html.xml
odoo14_addon_shopinvader_import_image-14.0.1.1.1.dist-info/METADATA
odoo14_addon_shopinvader_import_image-14.0.1.1.1.dist-info/WHEEL
odoo14_addon_shopinvader_import_image-14.0.1.1.1.dist-info/top_level.txt
odoo14_addon_shopinvader_import_image-14.0.1.1.1.dist-info/RECORD
