Metadata-Version: 2.1
Name: odoo14-addon-shopinvader-import-image
Version: 14.0.1.1.1
Summary: Import product images
Home-page: https://github.com/shopinvader/odoo-shopinvader
Author: Akretion, Camptocamp
License: AGPL-3
Platform: UNKNOWN
Classifier: Programming Language :: Python
Classifier: Framework :: Odoo
Classifier: License :: OSI Approved :: GNU Affero General Public License v3
Requires-Python: >=3.6
Requires-Dist: odoo14-addon-shopinvader-image
Requires-Dist: odoo (<14.1dev,>=14.0a)
Requires-Dist: python-magic
Requires-Dist: validators
